cb_badges/__init__.py
cb_badges/cli.py
cb_badges/data/fonts/hack/Hack-Bold.ttf
cb_badges/data/fonts/hack/Hack-BoldItalic.ttf
cb_badges/data/fonts/hack/Hack-Italic.ttf
cb_badges/data/fonts/hack/Hack-Regular.ttf
cb_badges/data/fonts/inter/Inter-Black.otf
cb_badges/data/fonts/inter/Inter-BlackItalic.otf
cb_badges/data/fonts/inter/Inter-Bold.otf
cb_badges/data/fonts/inter/Inter-BoldItalic.otf
cb_badges/data/fonts/inter/Inter-ExtraBold.otf
cb_badges/data/fonts/inter/Inter-ExtraBoldItalic.otf
cb_badges/data/fonts/inter/Inter-ExtraLight.otf
cb_badges/data/fonts/inter/Inter-ExtraLightItalic.otf
cb_badges/data/fonts/inter/Inter-Italic.otf
cb_badges/data/fonts/inter/Inter-Light.otf
cb_badges/data/fonts/inter/Inter-LightItalic.otf
cb_badges/data/fonts/inter/Inter-Medium.otf
cb_badges/data/fonts/inter/Inter-MediumItalic.otf
cb_badges/data/fonts/inter/Inter-Regular.otf
cb_badges/data/fonts/inter/Inter-SemiBold.otf
cb_badges/data/fonts/inter/Inter-SemiBoldItalic.otf
cb_badges/data/fonts/inter/Inter-Thin.otf
cb_badges/data/fonts/inter/Inter-ThinItalic.otf
cb_badges/data/templates/codeberg/config.json
cb_badges/data/templates/codeberg/template.j2
cb_badges/data/templates/codeberg/themes/dark.json
cb_badges/data/templates/codeberg/themes/legacy.json
cb_badges/data/templates/codeberg/themes/light.json
cb_badges/data/templates/standard/config.json
cb_badges/data/templates/standard/template.j2
cb_badges/data/templates/standard/themes/blue.json
cb_badges/data/templates/standard/themes/gray.json
cb_badges/data/templates/standard/themes/green.json
cb_badges/data/templates/standard/themes/lightblue.json
cb_badges/data/templates/standard/themes/lime.json
cb_badges/data/templates/standard/themes/orange.json
cb_badges/data/templates/standard/themes/purple.json
cb_badges/data/templates/standard/themes/red.json
cb_badges/data/templates/standard/themes/rose.json
cb_badges/data/templates/standard/themes/teal.json
cb_badges/utils/__init__.py
cb_badges/utils/cairo.py
cb_badges/utils/svg.py
cb_badges-0.3.1.dist-info/LICENSE
cb_badges-0.3.1.dist-info/METADATA
cb_badges-0.3.1.dist-info/WHEEL
cb_badges-0.3.1.dist-info/entry_points.txt
cb_badges-0.3.1.dist-info/top_level.txt
cb_badges-0.3.1.dist-info/RECORD
