Metadata-Version: 2.1
Name: cb-badges
Version: 0.3.1
Summary: UNKNOWN
Home-page: https://codeberg.org/S1SYPHOS/cb-badges
Author: Martin Folkers
Author-email: hello@twobrain.io
License: MIT
Project-URL: Issues, https://codeberg.org/S1SYPHOS/cb-badges/issues
Platform: UNKNOWN
Classifier: Programming Language :: Python :: 3
Classifier: License :: OSI Approved :: MIT License
Classifier: Operating System :: OS Independent
Requires-Python: >= 3.7
License-File: LICENSE
Requires-Dist: bs4
Requires-Dist: click
Requires-Dist: diskcache
Requires-Dist: font-line
Requires-Dist: jinja2
Requires-Dist: lxml
Requires-Dist: pycairo
Requires-Dist: pytest
Requires-Dist: requests
Requires-Dist: svgpathtools
